py_easy_rest/__init__.py
py_easy_rest/caches.py
py_easy_rest/dictionary_utils.py
py_easy_rest/exceptions.py
py_easy_rest/repos.py
py_easy_rest/service.py
py_easy_rest-0.4.7.dist-info/METADATA
py_easy_rest-0.4.7.dist-info/WHEEL
py_easy_rest-0.4.7.dist-info/top_level.txt
py_easy_rest-0.4.7.dist-info/RECORD
