Metadata-Version: 2.1
Name: py-easy-rest
Version: 0.4.7
Summary: The simplest way to have a rest api
Author: Jean Pinzon
Author-email: jean.pinzon1@gmail.com
Classifier: Programming Language :: Python :: 3
Classifier: License :: OSI Approved :: MIT License
Classifier: Operating System :: OS Independent
Requires-Python: >=3.8
Requires-Dist: jsonschema (==4.4.0)
Requires-Dist: sanic (==22.3.1)
Requires-Dist: sanic-ext (==22.3.1)
Provides-Extra: tests
Requires-Dist: sanic-testing (==22.3.0) ; extra == 'tests'
Requires-Dist: pytest (==7.1.2) ; extra == 'tests'
Requires-Dist: pytest-asyncio (==0.18.3) ; extra == 'tests'
Requires-Dist: pytest-cov (==3.0.0) ; extra == 'tests'
Requires-Dist: flake8 (==4.0.1) ; extra == 'tests'
Requires-Dist: aiounittest (==1.4.1) ; extra == 'tests'
Requires-Dist: twine (==4.0.0) ; extra == 'tests'
Requires-Dist: build (==0.7.0) ; extra == 'tests'
